qbt/__init__.py
qbt/cli.py
qbt-0.0.1.dist-info/entry_points.txt
qbt-0.0.1.dist-info/WHEEL
qbt-0.0.1.dist-info/METADATA
qbt-0.0.1.dist-info/RECORD
