Metadata-Version: 2.1
Name: qbt
Version: 0.0.1
Summary: QBT
Requires-Python: >=3.11
